CHANGELOG.md
LICENSE
README.md
vpype/__init__.py
vpype/config.py
vpype/filters.py
vpype/fonts/astrology.pickle
vpype/fonts/cursive.pickle
vpype/fonts/cyrilc_1.pickle
vpype/fonts/cyrillic.pickle
vpype/fonts/futural.pickle
vpype/fonts/futuram.pickle
vpype/fonts/gothgbt.pickle
vpype/fonts/gothgrt.pickle
vpype/fonts/gothiceng.pickle
vpype/fonts/gothicger.pickle
vpype/fonts/gothicita.pickle
vpype/fonts/gothitt.pickle
vpype/fonts/greek.pickle
vpype/fonts/greekc.pickle
vpype/fonts/greeks.pickle
vpype/fonts/japanese.pickle
vpype/fonts/markers.pickle
vpype/fonts/mathlow.pickle
vpype/fonts/mathupp.pickle
vpype/fonts/meteorology.pickle
vpype/fonts/music.pickle
vpype/fonts/rowmand.pickle
vpype/fonts/rowmans.pickle
vpype/fonts/rowmant.pickle
vpype/fonts/scriptc.pickle
vpype/fonts/scripts.pickle
vpype/fonts/symbolic.pickle
vpype/fonts/timesg.pickle
vpype/fonts/timesi.pickle
vpype/fonts/timesib.pickle
vpype/fonts/timesr.pickle
vpype/fonts/timesrb.pickle
vpype/geometry.py
vpype/io.py
vpype/line_index.py
vpype/metadata.py
vpype/model.py
vpype/primitives.py
vpype/text.py
vpype/utils.py
vpype/vpype_config.toml
vpype_cli/__init__.py
vpype_cli/__main__.py
vpype_cli/blocks.py
vpype_cli/cli.py
vpype_cli/debug.py
vpype_cli/decorators.py
vpype_cli/eval.py
vpype_cli/filters.py
vpype_cli/frames.py
vpype_cli/generators.py
vpype_cli/layerops.py
vpype_cli/metadata.py
vpype_cli/operations.py
vpype_cli/primitives.py
vpype_cli/read.py
vpype_cli/script.py
vpype_cli/show.py
vpype_cli/state.py
vpype_cli/substitution.py
vpype_cli/text.py
vpype_cli/transforms.py
vpype_cli/types.py
vpype_cli/write.py
vpype_viewer/__init__.py
vpype_viewer/_painters.py
vpype_viewer/_scales.py
vpype_viewer/_utils.py
vpype_viewer/engine.py
vpype_viewer/image/__init__.py
vpype_viewer/qtviewer/__init__.py
vpype_viewer/qtviewer/resources/eye-outline-dark.svg
vpype_viewer/qtviewer/resources/eye-outline.svg
vpype_viewer/qtviewer/resources/fit-to-page-outline-dark.svg
vpype_viewer/qtviewer/resources/fit-to-page-outline.svg
vpype-1.13.0.dist-info/LICENSE
vpype-1.13.0.dist-info/METADATA
vpype-1.13.0.dist-info/WHEEL
vpype-1.13.0.dist-info/entry_points.txt
vpype-1.13.0.dist-info/RECORD
