Metadata-Version: 2.1
Name: vpype
Version: 1.13.0
Summary: The Swiss Army knife of vector graphics for pen plotters
Home-page: https://github.com/abey79/vpype
License: MIT
Author: Antoine Beyeler
Author-email: abeyeler@ab-ware.com
Requires-Python: >=3.9,<3.12
Classifier: Development Status :: 5 - Production/Stable
Classifier: Environment :: Console
Classifier: License :: OSI Approved :: MIT License
Classifier: Programming Language :: Python :: 3
Classifier: Programming Language :: Python :: 3.9
Classifier: Programming Language :: Python :: 3.10
Classifier: Programming Language :: Python :: 3.11
Classifier: Topic :: Artistic Software
Classifier: Topic :: Multimedia :: Graphics
Provides-Extra: all
Requires-Dist: Pillow (>=9.0.1) ; extra == "all"
Requires-Dist: PySide6 (>=6.4.0.1) ; extra == "all"
Requires-Dist: Shapely[vectorized] (>=1.8.2)
Requires-Dist: asteval (>=0.9.26)
Requires-Dist: cachetools (>=4.2.2)
Requires-Dist: click (>=8.0.1,<8.2.0)
Requires-Dist: glcontext (>=2.3.2) ; extra == "all"
Requires-Dist: matplotlib (>=3.3.2) ; extra == "all"
Requires-Dist: moderngl (>=5.6.2,!=5.7.1,!=5.7.2) ; extra == "all"
Requires-Dist: multiprocess (>=0.70.11)
Requires-Dist: numpy (>=1.20)
Requires-Dist: pnoise (>=0.2.0)
Requires-Dist: scipy (>=1.6)
Requires-Dist: svgelements (>=1.6.10)
Requires-Dist: svgwrite (>=1.4,<1.5)
Requires-Dist: tomli (>=2.0.0)
Project-URL: Documentation, https://vpype.readthedocs.io/en/latest/
